iter2/__init__.py
iter2/option.py
iter2/sequence_builders.py
iter2/utils.py
iter2/wrapped_algorithms.py
iter2/algorithms/__init__.py
iter2/algorithms/extra.py
iter2/algorithms/folding.py
iter2/algorithms/merging.py
iter2/algorithms/predicate_on_sequence.py
iter2/algorithms/searching.py
iter2/algorithms/sequence_to_groups.py
iter2/algorithms/sequence_to_sequence.py
iter2/algorithms/splitting.py
iter2/iterators/__init__.py
iter2/iterators/iterator2.py
iter2/iterators/spy_iterator.py
ter2-1.1.dist-info/METADATA
ter2-1.1.dist-info/WHEEL
ter2-1.1.dist-info/top_level.txt
ter2-1.1.dist-info/RECORD
